remote_import/remote_importer.py
remote_import/version.py
remote_import-0.2.dist-info/LICENSE
remote_import-0.2.dist-info/METADATA
remote_import-0.2.dist-info/WHEEL
remote_import-0.2.dist-info/top_level.txt
remote_import-0.2.dist-info/RECORD
